zeloscloud/__init__.py
zeloscloud-0.0.1.dist-info/METADATA
zeloscloud-0.0.1.dist-info/WHEEL
zeloscloud-0.0.1.dist-info/top_level.txt
zeloscloud-0.0.1.dist-info/RECORD
